cb_signal_tui/__init__.py
cb_signal_tui/__main__.py
cb_signal_tui/backtest.py
cb_signal_tui/config.py
cb_signal_tui/ga_optimizer.py
cb_signal_tui/indicators.py
cb_signal_tui/scanner.py
cb_signal_tui/utils.py
cb_signal_tui-1.4.1.dist-info/licenses/LICENSE
cb_signal_tui-1.4.1.dist-info/METADATA
cb_signal_tui-1.4.1.dist-info/WHEEL
cb_signal_tui-1.4.1.dist-info/entry_points.txt
cb_signal_tui-1.4.1.dist-info/top_level.txt
cb_signal_tui-1.4.1.dist-info/RECORD
