Metadata-Version: 2.4
Name: cb-signal-tui
Version: 1.4.1
Summary: A high-performance terminal-native crypto signal scanner with live Z-score analytics, DEAP-based RL tuning, and automated backtesting.
Author-email: LoQiseaking69 <REEL0112358.13@proton.me>
License: BSD 3-Clause License
Classifier: Development Status :: 5 - Production/Stable
Classifier: Intended Audience :: Developers
Classifier: License :: OSI Approved :: BSD License
Classifier: Programming Language :: Python :: 3
Classifier: Programming Language :: Python :: 3.9
Classifier: Programming Language :: Python :: 3.10
Classifier: Programming Language :: Python :: 3.11
Classifier: Operating System :: OS Independent
Classifier: Environment :: Console
Classifier: Topic :: Utilities
Classifier: Topic :: Office/Business :: Financial
Classifier: Topic :: Scientific/Engineering :: Artificial Intelligence
Classifier: Topic :: Scientific/Engineering :: Information Analysis
Requires-Python: >=3.9
License-File: LICENSE
Requires-Dist: aiohttp
Requires-Dist: aiosqlite
Requires-Dist: pandas
Requires-Dist: numpy
Requires-Dist: pyttsx3
Requires-Dist: rich
Requires-Dist: scipy
Requires-Dist: deap
Requires-Dist: tabulate
Dynamic: license-file
